{
    "type": "file",
    "name": "KML-Points", 
    "exchangeType": "file-based", 
    "part": "Points",
    "version": "2.2",
    "refreshRate": "[ISO8601 timespan]",
    "privacy": "A",
    "confidentiality": "C",
    "interoperability": "E",
    "domain": "D",
    "mediumType": "xml-file",
    "retentionPeriod": "[ISO8601 timespan]",
    "externalReference": "https://developers.google.com/kml/documentation/kmlreference",
    "bbversion": 1,
    "description": "KML file only containing locations<br>Keyhole Markup Language (KML) is an XML notation for expressing geographic annotation and visualization within two-dimensional maps and three-dimensional Earth browsers. KML was developed for use with Google Earth, which was originally named Keyhole Earth Viewer. It was created by Keyhole, Inc, which was acquired by Google in 2004. KML became an international standard of the Open Geospatial Consortium in 2008"
}