[ 
{
    "id": "availability-per-parkingspot",
    "externalReference": "",
    "story": {
        "asA": "city",
        "iWouldLikeTo": "determine the distribution of assets",
        "inOrderTo": "redistribute assets to create a more inclusive supply"
    },
    "termsAndConditions": [],
    "contract": [],
    "sharing": [],
    "authentication": [],
    "transport": [],
    "storage": [],
    "security": [],
    "combinations": [
        "publish-stations",
        "publish-preferred-parking-zones"
    ],
    "tags": [
        "public-space:distribution",
        "assets:availability",
        "mode:step",
        "mode:scooter",
        "mode:bike",
        "mode:shared-bike",
        "mode:car",
        "mode:shared-car"
    ]
}, 
{
  "id": "availability",
  "externalReference": "https://airtable.com/shrPf4QvORkjZmHIs/tblzFfU6fxQm5Sdhm/viwsiyw4MNx5CHmFI/recxqdTNFnleDcUHG",
  "story": {
    "asA": "city",
    "iWouldLikeTo": "get insight in availability of mobility services",
    "inOrderTo": "serve our citizens by redistributing mobility services"
  },
  "benefits": [
    {
      "to": "cities",
      "items": [
        "The citizens do have a higher availability of mobility assets"
      ]
    }
  ],
  "problemsSolved": [
    {
      "to": "cities",
      "items": [
        "Shortage by mispositioning of mobility assets"
      ]
    }
  ],
  "standards": [
    "GBFS-free-bike-status",
    "TOMP-available-assets",
    "MDS-provider-vehicles-without-ids"
  ],
  "termsAndConditions": [
    "BIO"
  ],
  "contract": [
    "DPA"
  ],
  "sharing": [],
  "authentication": [],
  "transport": [],
  "storage": [],
  "security": [
    "iso-27001.json"
  ],
  "combinations": [],
  "tags": [
    "public-space:distribution",
    "assets:availability",
    "mode:bike",
    "mode:car",
    "mode:shared-car"
  ],
  "not-used-tags": [
    "public-space:parking-pressure",
    "public-space:nuisances",
    "assets:demand",
    "assets:usage",
    "assets:trips",
    "safety:accidents",
    "safety:vandalism",
    "environmental:green-deal-goals",
    "environmental:emissions",
    "environmental:noise-pollution"
  ]
}, 
{
    "id": "operating-area",
    "externalReference": "",
    "tags": ["public-space:distribution"],
    "story": {
        "asA": "city",
        "iWouldLikeTo": "publish the operational area for transport operators",
        "inOrderTo": "maintain the order"
    }
}, 
{
    "id": "publish-preferred-parking-zones",
    "externalReference": "",
    "tags": [
        "public-space:parking-pressure",
        "public-space:nuisances",
        "public-space:distribution"
    ],
    "story": {
        "asA": "city",
        "iWouldLikeTo": "publish the preferred parking zones",
        "inOrderTo": "manage the usage of public space"
    }
}, 
{
    "id": "publish-stations",
    "externalReference": "",
    "tags": ["public-space:distribution", "public-space:parking-pressure"],
    "story": {
        "asA": "city",
        "iWouldLikeTo": "publish the assigned station locations for transport operators",
        "inOrderTo": "maintain the order"
    }
}] 
