{
    "type": "standard",
    "name": "MDS-provider-stops-20",
    "exchangeType": "API", 
    "part": "/stops",
    "url": "[url]",
    "version": "[2.0]",
    "mediumType": "API",
    "privacy": "B",
    "confidentiality": "B",
    "interoperability": "A",
    "domain": "A",
    "refreshRate": "0",
    "retentionPeriod": "[ISO8601 timespan]",
    "externalReference": "https://github.com/openmobilityfoundation/mobility-data-specification/tree/main/provider",
    "bbversion": 1, 
    "fieldModifications": [
        {
            "field": "devices",
            "exception": "exposed"
        }
    ],
    "conflicts": [
        "reveals_personal_trip_data"
    ],
    "description": "Stop information should be updated on a near-realtime basis by providers who operate docked mobility devices in a given municipality.<br>The Mobility Data Specification (MDS), a project of the Open Mobility Foundation (OMF), is a set of Application Programming Interfaces (APIs) focused on shared mobility services such as dockless scooters, bicycles, mopeds, and carshare, and inspired by projects like GTFS and GBFS.",
    "conditionalRequiredEndPoints": [ "MDS-geographies" ]
}