{
    "type": "standard",
    "name": "GBFS-free-bike-status",
    "displayName": "GBFS - Free bike status",
    "exchangeType": "[API,file-based]", 
    "mediumType": "json-file",
    "part": "free_bike_status.json",

    "externalReference": "https://github.com/NABSA/gbfs/blob/master/gbfs.md#vehicle_statusjson",
    "description": "This part contains the available assets. <br>The General Bikeshare Feed Specification, known as GBFS, is the open data standard for shared mobility. GBFS makes real-time data feeds in a uniform format publicly available online, with an emphasis on findability. GBFS is intended to make information publicly available online; therefore information that is personally identifiable is not currently and will not become part of the core specification.",
    "version": "[1.0,1.1,2.0]",
    "url": "[url]",
    "refreshRate": "[ISO8601 timespan]",

    "privacy": "A",
    "confidentiality": "B",
    "interoperability": "A",
    "domain": "B",

    "fieldModifications": [],
    "retentionPeriod": "[ISO8601 timespan]",
    "bbversion": 1
}