{
    "id": "parking-area-performance",
    "externalReference": "https://airtable.com/shrPf4QvORkjZmHIs/tblzFfU6fxQm5Sdhm/viwsiyw4MNx5CHmFI/recKEQoOBpKQdTyoU",
    "tags": ["public-space:parking-usage"],
    "story": {
        "asA": "city",
        "iWouldLikeTo": "get insights in the location and performance of all designated parking areas",
        "inOrderTo": "?"
    },
    "standards": [
        "MDS-provider-status_changes",
        "MDS-provider-status_changes-without-ids",
        "GBFS-station_information",
        "GBFS-station_status",
        "GBFS-free-bike-status",
        "GBFS-vehicle-status",
        "TOMP-stations",
        "TOMP-available-assets",
        "SPDP-dynamic",
        "SPDP-static"
    ]
}